purrency.py
purrency-0.3.dist-info/WHEEL
purrency-0.3.dist-info/METADATA
purrency-0.3.dist-info/RECORD
