Metadata-Version: 1.2
Name: purrency
Version: 0.3
Summary: Simple currency parser with Python
Home-page: http://github.com/fuchida/purrency
License: UNKNOWN
Author: Abdul Salim
Author-email: abdlsalim@gmail.com
